{
  "updated_at": "2026-07-21 05:00:36",
  "tf_rights": [
    {
      "account": "F0200006398037",
      "account_balance": "1486673",
      "floating_pl": "0",
      "futures_close_pl": "-930",
      "intraday_unrealized": "0",
      "equity": "1486673",
      "excess_margin": "1486673",
      "initial_margin": "0",
      "maintenance_margin": "0",
      "risk_indicator": "100",
      "yesterday_balance": "1488017",
      "realized_fee": "220",
      "transaction_tax": "194",
      "available_balance": "1486673"
    }
  ],
  "of_rights": [
    {
      "account": "F0200006398037",
      "currency": "NTD(基幣)",
      "account_equity": "350629",
      "account_balance": "350629",
      "futures_floating_pl": "0",
      "futures_close_pl_today": "-4016",
      "intraday_unrealized": "0",
      "initial_margin": "0",
      "maintenance_margin": "0",
      "risk_indicator": "",
      "withdrawable_margin": "350629",
      "realized_fee": "48",
      "previous_day_balance": "354694",
      "reference_rate": "1"
    }
  ],
  "tf_positions": [],
  "of_positions": []
}