[
  {
    "date": "2026-04-15",
    "tf_close_pl": 84.0,
    "tf_float_pl": 0.0,
    "tf_total_pl": 84.0,
    "of_close_pl": 0.0,
    "of_float_pl": 0.0,
    "of_total_pl": 0.0,
    "tf_equity": 0.0,
    "of_equity": 0.0,
    "of_currency": "NTD",
    "of_ref_rate": 1.0
  },
  {
    "date": "2026-04-16",
    "tf_close_pl": -1478.0,
    "tf_float_pl": 0.0,
    "tf_total_pl": -1478.0,
    "of_close_pl": 0.0,
    "of_float_pl": 0.0,
    "of_total_pl": 0.0,
    "tf_equity": 0.0,
    "of_equity": 0.0,
    "of_currency": "NTD",
    "of_ref_rate": 1.0
  },
  {
    "date": "2026-04-17",
    "tf_close_pl": -5478.0,
    "tf_float_pl": 0.0,
    "tf_total_pl": -5478.0,
    "of_close_pl": 0.0,
    "of_float_pl": 0.0,
    "of_total_pl": 0.0,
    "tf_equity": 0.0,
    "of_equity": 0.0,
    "of_currency": "NTD",
    "of_ref_rate": 1.0
  },
  {
    "date": "2026-04-20",
    "tf_close_pl": -1986.0,
    "tf_float_pl": 0.0,
    "tf_total_pl": -1986.0,
    "of_close_pl": 0.0,
    "of_float_pl": 0.0,
    "of_total_pl": 0.0,
    "tf_equity": 0.0,
    "of_equity": 0.0,
    "of_currency": "NTD",
    "of_ref_rate": 1.0
  },
  {
    "date": "2026-04-21",
    "tf_close_pl": -4144.0,
    "tf_float_pl": 0.0,
    "tf_total_pl": -4144.0,
    "of_close_pl": 0.0,
    "of_float_pl": 0.0,
    "of_total_pl": 0.0,
    "tf_equity": 0.0,
    "of_equity": 0.0,
    "of_currency": "NTD",
    "of_ref_rate": 1.0
  },
  {
    "date": "2026-04-22",
    "tf_close_pl": -3706.0,
    "tf_float_pl": 0.0,
    "tf_total_pl": -3706.0,
    "of_close_pl": 0.0,
    "of_float_pl": 0.0,
    "of_total_pl": 0.0,
    "tf_equity": 0.0,
    "of_equity": 0.0,
    "of_currency": "NTD",
    "of_ref_rate": 1.0
  },
  {
    "date": "2026-04-23",
    "tf_close_pl": 20662.0,
    "tf_float_pl": 0.0,
    "tf_total_pl": 20662.0,
    "of_close_pl": 0.0,
    "of_float_pl": 0.0,
    "of_total_pl": 0.0,
    "tf_equity": 0.0,
    "of_equity": 0.0,
    "of_currency": "NTD",
    "of_ref_rate": 1.0
  },
  {
    "date": "2026-04-27",
    "tf_close_pl": 19988.0,
    "tf_float_pl": 0.0,
    "tf_total_pl": 19988.0,
    "of_close_pl": 0.0,
    "of_float_pl": 0.0,
    "of_total_pl": 0.0,
    "tf_equity": 0.0,
    "of_equity": 0.0,
    "of_currency": "NTD",
    "of_ref_rate": 1.0
  },
  {
    "date": "2026-04-29",
    "tf_close_pl": 3126.0,
    "tf_float_pl": 0.0,
    "tf_total_pl": 3126.0,
    "of_close_pl": 0.0,
    "of_float_pl": 0.0,
    "of_total_pl": 0.0,
    "tf_equity": 0.0,
    "of_equity": 0.0,
    "of_currency": "NTD",
    "of_ref_rate": 1.0
  },
  {
    "date": "2026-05-05",
    "tf_close_pl": 19978.0,
    "tf_float_pl": 0.0,
    "tf_total_pl": 19978.0,
    "of_close_pl": 0.0,
    "of_float_pl": 0.0,
    "of_total_pl": 0.0,
    "tf_equity": 0.0,
    "of_equity": 0.0,
    "of_currency": "NTD",
    "of_ref_rate": 1.0
  },
  {
    "date": "2026-05-06",
    "tf_close_pl": 31424.0,
    "tf_float_pl": 0.0,
    "tf_total_pl": 31424.0,
    "of_close_pl": 0.0,
    "of_float_pl": 0.0,
    "of_total_pl": 0.0,
    "tf_equity": 0.0,
    "of_equity": 0.0,
    "of_currency": "NTD",
    "of_ref_rate": 1.0
  },
  {
    "date": "2026-05-07",
    "tf_close_pl": 86370.0,
    "tf_float_pl": 0.0,
    "tf_total_pl": 86370.0,
    "of_close_pl": 0.0,
    "of_float_pl": 0.0,
    "of_total_pl": 0.0,
    "tf_equity": 0.0,
    "of_equity": 0.0,
    "of_currency": "NTD",
    "of_ref_rate": 1.0
  },
  {
    "date": "2026-05-08",
    "tf_close_pl": -1600.0,
    "tf_float_pl": 0.0,
    "tf_total_pl": -1600.0,
    "of_close_pl": 0.0,
    "of_float_pl": 0.0,
    "of_total_pl": 0.0,
    "tf_equity": 0.0,
    "of_equity": 0.0,
    "of_currency": "NTD",
    "of_ref_rate": 1.0
  },
  {
    "date": "2026-05-11",
    "tf_close_pl": -21176.0,
    "tf_float_pl": 0.0,
    "tf_total_pl": -21176.0,
    "of_close_pl": 0.0,
    "of_float_pl": 0.0,
    "of_total_pl": 0.0,
    "tf_equity": 0.0,
    "of_equity": 0.0,
    "of_currency": "NTD",
    "of_ref_rate": 1.0
  },
  {
    "date": "2026-05-12",
    "tf_close_pl": 2260.0,
    "tf_float_pl": 0.0,
    "tf_total_pl": 2260.0,
    "of_close_pl": 0.0,
    "of_float_pl": 0.0,
    "of_total_pl": 0.0,
    "tf_equity": 0.0,
    "of_equity": 0.0,
    "of_currency": "NTD",
    "of_ref_rate": 1.0
  },
  {
    "date": "2026-05-13",
    "tf_close_pl": -7792.0,
    "tf_float_pl": 0.0,
    "tf_total_pl": -7792.0,
    "of_close_pl": 0.0,
    "of_float_pl": 0.0,
    "of_total_pl": 0.0,
    "tf_equity": 0.0,
    "of_equity": 0.0,
    "of_currency": "NTD",
    "of_ref_rate": 1.0
  },
  {
    "date": "2026-05-14",
    "tf_close_pl": 0.0,
    "tf_float_pl": 0.0,
    "tf_total_pl": 0.0,
    "of_close_pl": -110.27,
    "of_float_pl": 0.0,
    "of_total_pl": -110.27,
    "tf_equity": 0.0,
    "of_equity": 0.0,
    "of_currency": "NTD",
    "of_ref_rate": 1.0
  },
  {
    "date": "2026-05-15",
    "tf_close_pl": 0.0,
    "tf_float_pl": 0.0,
    "tf_total_pl": 0.0,
    "of_close_pl": -24948.14,
    "of_float_pl": 0.0,
    "of_total_pl": -24948.14,
    "tf_equity": 0.0,
    "of_equity": 0.0,
    "of_currency": "NTD",
    "of_ref_rate": 1.0
  },
  {
    "date": "2026-05-18",
    "tf_close_pl": 0.0,
    "tf_float_pl": 0.0,
    "tf_total_pl": 0.0,
    "of_close_pl": -29321.08,
    "of_float_pl": 0.0,
    "of_total_pl": -29321.08,
    "tf_equity": 0.0,
    "of_equity": 0.0,
    "of_currency": "NTD",
    "of_ref_rate": 1.0
  },
  {
    "date": "2026-05-19",
    "tf_close_pl": 0.0,
    "tf_float_pl": 0.0,
    "tf_total_pl": 0.0,
    "of_close_pl": -33311.62,
    "of_float_pl": 0.0,
    "of_total_pl": -33311.62,
    "tf_equity": 0.0,
    "of_equity": 0.0,
    "of_currency": "NTD",
    "of_ref_rate": 1.0
  },
  {
    "date": "2026-05-20",
    "tf_close_pl": 0.0,
    "tf_float_pl": 0.0,
    "tf_total_pl": 0.0,
    "of_close_pl": 47.47,
    "of_float_pl": 0.0,
    "of_total_pl": 47.47,
    "tf_equity": 0.0,
    "of_equity": 0.0,
    "of_currency": "NTD",
    "of_ref_rate": 1.0
  },
  {
    "date": "2026-05-21",
    "tf_close_pl": 70888.0,
    "tf_float_pl": 0.0,
    "tf_total_pl": 70888.0,
    "of_close_pl": 0.0,
    "of_float_pl": 0.0,
    "of_total_pl": 0.0,
    "tf_equity": 0.0,
    "of_equity": 0.0,
    "of_currency": "NTD",
    "of_ref_rate": 1.0
  },
  {
    "date": "2026-05-22",
    "tf_close_pl": 1722.0,
    "tf_float_pl": 0.0,
    "tf_total_pl": 1722.0,
    "of_close_pl": 0.0,
    "of_float_pl": 0.0,
    "of_total_pl": 0.0,
    "tf_equity": 0.0,
    "of_equity": 0.0,
    "of_currency": "NTD",
    "of_ref_rate": 1.0
  },
  {
    "date": "2026-05-25",
    "tf_close_pl": 164571.0,
    "tf_float_pl": 0.0,
    "tf_total_pl": 164571.0,
    "of_close_pl": 0.0,
    "of_float_pl": 0.0,
    "of_total_pl": 0.0,
    "tf_equity": 0.0,
    "of_equity": 0.0,
    "of_currency": "NTD",
    "of_ref_rate": 1.0
  },
  {
    "date": "2026-05-26",
    "tf_close_pl": 0.0,
    "tf_float_pl": 0.0,
    "tf_total_pl": 0.0,
    "of_close_pl": 57337.44,
    "of_float_pl": 0.0,
    "of_total_pl": 57337.44,
    "tf_equity": 0.0,
    "of_equity": 0.0,
    "of_currency": "NTD",
    "of_ref_rate": 1.0
  },
  {
    "date": "2026-05-27",
    "tf_close_pl": -43122.0,
    "tf_float_pl": 0.0,
    "tf_total_pl": -43122.0,
    "of_close_pl": -5638.1,
    "of_float_pl": 0.0,
    "of_total_pl": -5638.1,
    "tf_equity": 0.0,
    "of_equity": 0.0,
    "of_currency": "NTD",
    "of_ref_rate": 1.0
  },
  {
    "date": "2026-05-28",
    "tf_close_pl": -89711.0,
    "tf_float_pl": 0.0,
    "tf_total_pl": -89711.0,
    "of_close_pl": -5778.52,
    "of_float_pl": 0.0,
    "of_total_pl": -5778.52,
    "tf_equity": 0.0,
    "of_equity": 0.0,
    "of_currency": "NTD",
    "of_ref_rate": 1.0
  },
  {
    "date": "2026-06-01",
    "tf_close_pl": 234670.0,
    "tf_float_pl": 0.0,
    "tf_total_pl": 234670.0,
    "of_close_pl": 0.0,
    "of_float_pl": 0.0,
    "of_total_pl": 0.0,
    "tf_equity": 0.0,
    "of_equity": 0.0,
    "of_currency": "NTD",
    "of_ref_rate": 1.0
  },
  {
    "date": "2026-06-02",
    "tf_close_pl": -8052.0,
    "tf_float_pl": 0.0,
    "tf_total_pl": -8052.0,
    "of_close_pl": 0.0,
    "of_float_pl": 0.0,
    "of_total_pl": 0.0,
    "tf_equity": 0.0,
    "of_equity": 0.0,
    "of_currency": "NTD",
    "of_ref_rate": 1.0
  },
  {
    "date": "2026-06-03",
    "tf_close_pl": -71377.0,
    "tf_float_pl": 0.0,
    "tf_total_pl": -71377.0,
    "of_close_pl": 65756.82,
    "of_float_pl": 0.0,
    "of_total_pl": 65756.82,
    "tf_equity": 0.0,
    "of_equity": 0.0,
    "of_currency": "NTD",
    "of_ref_rate": 1.0
  },
  {
    "date": "2026-06-04",
    "tf_close_pl": 0.0,
    "tf_float_pl": 0.0,
    "tf_total_pl": 0.0,
    "of_close_pl": -10350.34,
    "of_float_pl": 0.0,
    "of_total_pl": -10350.34,
    "tf_equity": 0.0,
    "of_equity": 0.0,
    "of_currency": "NTD",
    "of_ref_rate": 1.0
  },
  {
    "date": "2026-06-05",
    "tf_close_pl": 0.0,
    "tf_float_pl": 0.0,
    "tf_total_pl": 0.0,
    "of_close_pl": -13817.53,
    "of_float_pl": 0.0,
    "of_total_pl": -13817.53,
    "tf_equity": 0.0,
    "of_equity": 0.0,
    "of_currency": "NTD",
    "of_ref_rate": 1.0
  },
  {
    "date": "2026-06-08",
    "tf_close_pl": 50558.0,
    "tf_float_pl": 0.0,
    "tf_total_pl": 50558.0,
    "of_close_pl": 0.0,
    "of_float_pl": 0.0,
    "of_total_pl": 0.0,
    "tf_equity": 0.0,
    "of_equity": 0.0,
    "of_currency": "NTD",
    "of_ref_rate": 1.0
  },
  {
    "date": "2026-06-09",
    "tf_close_pl": 0.0,
    "tf_float_pl": 0.0,
    "tf_total_pl": 0.0,
    "of_close_pl": -12033.31,
    "of_float_pl": 0.0,
    "of_total_pl": -12033.31,
    "tf_equity": 0.0,
    "of_equity": 0.0,
    "of_currency": "NTD",
    "of_ref_rate": 1.0
  },
  {
    "date": "2026-06-10",
    "tf_close_pl": -8034.0,
    "tf_float_pl": 0.0,
    "tf_total_pl": -8034.0,
    "of_close_pl": 0.0,
    "of_float_pl": 0.0,
    "of_total_pl": 0.0,
    "tf_equity": 0.0,
    "of_equity": 0.0,
    "of_currency": "NTD",
    "of_ref_rate": 1.0
  },
  {
    "date": "2026-06-11",
    "tf_close_pl": 2274.0,
    "tf_float_pl": 0.0,
    "tf_total_pl": 2274.0,
    "of_close_pl": 0.0,
    "of_float_pl": 0.0,
    "of_total_pl": 0.0,
    "tf_equity": 0.0,
    "of_equity": 0.0,
    "of_currency": "NTD",
    "of_ref_rate": 1.0
  },
  {
    "date": "2026-06-12",
    "tf_close_pl": -119873.0,
    "tf_float_pl": 0.0,
    "tf_total_pl": -119873.0,
    "of_close_pl": 0.0,
    "of_float_pl": 0.0,
    "of_total_pl": 0.0,
    "tf_equity": 0.0,
    "of_equity": 0.0,
    "of_currency": "NTD",
    "of_ref_rate": 1.0
  },
  {
    "date": "2026-06-15",
    "tf_close_pl": -6190.0,
    "tf_float_pl": 4680.0,
    "tf_total_pl": -1510.0,
    "of_close_pl": 0.0,
    "of_float_pl": 244385.0,
    "of_total_pl": 244385.0,
    "tf_equity": 1495001.0,
    "of_equity": 832962.0,
    "of_currency": "NTD(基幣)",
    "of_ref_rate": 1.0
  },
  {
    "date": "2026-06-16",
    "tf_close_pl": -9990.0,
    "tf_float_pl": 0.0,
    "tf_total_pl": -9990.0,
    "of_close_pl": 229571.0,
    "of_float_pl": 2871.0,
    "of_total_pl": 232442.0,
    "tf_equity": 1480255.0,
    "of_equity": 820500.0,
    "of_currency": "NTD(基幣)",
    "of_ref_rate": 1.0
  },
  {
    "date": "2026-06-17",
    "tf_close_pl": 0.0,
    "tf_float_pl": 0.0,
    "tf_total_pl": 0.0,
    "of_close_pl": -88078.46,
    "of_float_pl": 0.0,
    "of_total_pl": -88078.46,
    "tf_equity": 0.0,
    "of_equity": 0.0,
    "of_currency": "NTD",
    "of_ref_rate": 1.0
  },
  {
    "date": "2026-06-18",
    "tf_close_pl": -40578.0,
    "tf_float_pl": 0.0,
    "tf_total_pl": -40578.0,
    "of_close_pl": 0.0,
    "of_float_pl": 0.0,
    "of_total_pl": 0.0,
    "tf_equity": 0.0,
    "of_equity": 0.0,
    "of_currency": "NTD",
    "of_ref_rate": 1.0
  },
  {
    "date": "2026-06-22",
    "tf_close_pl": 0.0,
    "tf_float_pl": 0.0,
    "tf_total_pl": 0.0,
    "of_close_pl": -32114.6,
    "of_float_pl": 0.0,
    "of_total_pl": -32114.6,
    "tf_equity": 0.0,
    "of_equity": 0.0,
    "of_currency": "NTD",
    "of_ref_rate": 1.0
  },
  {
    "date": "2026-06-23",
    "tf_close_pl": 0.0,
    "tf_float_pl": 0.0,
    "tf_total_pl": 0.0,
    "of_close_pl": -108049.35,
    "of_float_pl": 0.0,
    "of_total_pl": -108049.35,
    "tf_equity": 0.0,
    "of_equity": 0.0,
    "of_currency": "NTD",
    "of_ref_rate": 1.0
  },
  {
    "date": "2026-06-24",
    "tf_close_pl": -70751.0,
    "tf_float_pl": 0.0,
    "tf_total_pl": -70751.0,
    "of_close_pl": 0.0,
    "of_float_pl": 0.0,
    "of_total_pl": 0.0,
    "tf_equity": 0.0,
    "of_equity": 0.0,
    "of_currency": "NTD",
    "of_ref_rate": 1.0
  },
  {
    "date": "2026-06-25",
    "tf_close_pl": -28916.0,
    "tf_float_pl": 0.0,
    "tf_total_pl": -28916.0,
    "of_close_pl": 0.0,
    "of_float_pl": 0.0,
    "of_total_pl": 0.0,
    "tf_equity": 0.0,
    "of_equity": 0.0,
    "of_currency": "NTD",
    "of_ref_rate": 1.0
  },
  {
    "date": "2026-06-26",
    "tf_close_pl": 54792.0,
    "tf_float_pl": 0.0,
    "tf_total_pl": 54792.0,
    "of_close_pl": 0.0,
    "of_float_pl": 0.0,
    "of_total_pl": 0.0,
    "tf_equity": 0.0,
    "of_equity": 0.0,
    "of_currency": "NTD",
    "of_ref_rate": 1.0
  },
  {
    "date": "2026-06-29",
    "tf_close_pl": -58192.0,
    "tf_float_pl": 0.0,
    "tf_total_pl": -58192.0,
    "of_close_pl": 0.0,
    "of_float_pl": 0.0,
    "of_total_pl": 0.0,
    "tf_equity": 0.0,
    "of_equity": 0.0,
    "of_currency": "NTD",
    "of_ref_rate": 1.0
  },
  {
    "date": "2026-06-30",
    "tf_close_pl": -40602.0,
    "tf_float_pl": 0.0,
    "tf_total_pl": -40602.0,
    "of_close_pl": 0.0,
    "of_float_pl": 0.0,
    "of_total_pl": 0.0,
    "tf_equity": 0.0,
    "of_equity": 0.0,
    "of_currency": "NTD",
    "of_ref_rate": 1.0
  },
  {
    "date": "2026-07-01",
    "tf_close_pl": 0.0,
    "tf_float_pl": 0.0,
    "tf_total_pl": 0.0,
    "of_close_pl": 19006.44,
    "of_float_pl": 0.0,
    "of_total_pl": 19006.44,
    "tf_equity": 0.0,
    "of_equity": 0.0,
    "of_currency": "NTD",
    "of_ref_rate": 1.0
  },
  {
    "date": "2026-07-02",
    "tf_close_pl": 0.0,
    "tf_float_pl": 0.0,
    "tf_total_pl": 0.0,
    "of_close_pl": -57088.92,
    "of_float_pl": 0.0,
    "of_total_pl": -57088.92,
    "tf_equity": 0.0,
    "of_equity": 0.0,
    "of_currency": "NTD",
    "of_ref_rate": 1.0
  },
  {
    "date": "2026-07-03",
    "tf_close_pl": 1472.0,
    "tf_float_pl": 0.0,
    "tf_total_pl": 1472.0,
    "of_close_pl": 0.0,
    "of_float_pl": 0.0,
    "of_total_pl": 0.0,
    "tf_equity": 0.0,
    "of_equity": 0.0,
    "of_currency": "NTD",
    "of_ref_rate": 1.0
  },
  {
    "date": "2026-07-06",
    "tf_close_pl": 28060.0,
    "tf_float_pl": -530.0,
    "tf_total_pl": 27530.0,
    "of_close_pl": 0.0,
    "of_float_pl": 11121.0,
    "of_total_pl": 11121.0,
    "tf_equity": 1402327.0,
    "of_equity": 479032.0,
    "of_currency": "NTD(基幣)",
    "of_ref_rate": 1.0
  },
  {
    "date": "2026-07-07",
    "tf_close_pl": 56230.0,
    "tf_float_pl": -1960.0,
    "tf_total_pl": 54270.0,
    "of_close_pl": 4342.0,
    "of_float_pl": 0.0,
    "of_total_pl": 4342.0,
    "tf_equity": 1456291.0,
    "of_equity": 472914.0,
    "of_currency": "NTD(基幣)",
    "of_ref_rate": 1.0
  }
]